{
    "identifier": "memory-box",
    "name": "Memory-Box",
    "type": "WebApplication",
    "applicationCategory": "Education",
    "title": "Memory-Box | Spaced Repetition",
    "subtitle": "Spaced Repetition Application",
    "headline": "Spaced Repetition Application",
    "description": "A spaced repetition web application for users to learn and share flashcards efficiently.",
    "technologies": {
        "server": [
            "Node.js",
            "Express.js"
        ],
        "hosting": [
            "Heroku"
        ],
        "data": [
            "PostgreSQL",
            "AWS S3"
        ],
        "frontEnd": [
            "React.js"
        ]
    },
    "inLanguage": "en",
    "dateCreated": "2017",
    "license": "https://www.gnu.org/licenses/gpl-3.0.html",
    "keywords": [
        "Space Repetition",
        "Memory",
        "Flashcards"
    ]
}
